sodaspark/__init__.py
sodaspark/_version.py
sodaspark/scan.py
soda_spark-0.3.3.dist-info/LICENSE
soda_spark-0.3.3.dist-info/METADATA
soda_spark-0.3.3.dist-info/WHEEL
soda_spark-0.3.3.dist-info/top_level.txt
soda_spark-0.3.3.dist-info/RECORD
