Metadata-Version: 2.1
Name: soda-spark
Version: 0.3.3
Summary: Soda SQL API for PySpark data frame
Home-page: https://github.com/sodadata/soda-spark
Author: Cor Zuurmond
Maintainer: Cor Zuurmond
Maintainer-email: corzuurmond@godatadriven.com
License: Apache 2.0
Project-URL: Source, https://github.com/sodadata/soda-spark
Project-URL: Tracker, https://github.com/sodadata/soda-spark/issues
Keywords: Data quality,Spark,Soda
Platform: any
Requires-Python: >=3.6
License-File: LICENSE
Requires-Dist: soda-sql-spark (~=2.1.9)
Requires-Dist: pyspark (~=3.0)
Provides-Extra: testing
Requires-Dist: pre-commit (>=2.14.1) ; extra == 'testing'
Requires-Dist: pytest (>=6.2.5) ; extra == 'testing'
Requires-Dist: pytest-spark (>=0.6.0) ; extra == 'testing'
Requires-Dist: pytest-cov (>=2.12.1) ; extra == 'testing'
